fastchatgpt
