Metadata-Version: 2.1
Name: fastchatgpt
Version: 0.0.8
Summary: fastchatgpt: A tool to interact with large language model(LLM)
License: Apache license
Platform: UNKNOWN
Requires-Python: >=3.6
License-File: LICENSE
